pracklrr/__init__.py
pracklrr/pracklrr.py
pracklrr-0.1.dist-info/METADATA
pracklrr-0.1.dist-info/WHEEL
pracklrr-0.1.dist-info/top_level.txt
pracklrr-0.1.dist-info/RECORD
